odoo/addons/stock_request_tier_validation/README.rst
odoo/addons/stock_request_tier_validation/__init__.py
odoo/addons/stock_request_tier_validation/__manifest__.py
odoo/addons/stock_request_tier_validation/data/stock_request_tier_definition.xml
odoo/addons/stock_request_tier_validation/i18n/es.po
odoo/addons/stock_request_tier_validation/i18n/it.po
odoo/addons/stock_request_tier_validation/i18n/stock_request_tier_validation.pot
odoo/addons/stock_request_tier_validation/i18n/zh_CN.po
odoo/addons/stock_request_tier_validation/models/__init__.py
odoo/addons/stock_request_tier_validation/models/stock_request.py
odoo/addons/stock_request_tier_validation/models/stock_request_order.py
odoo/addons/stock_request_tier_validation/models/tier_definition.py
odoo/addons/stock_request_tier_validation/readme/CONFIGURE.md
odoo/addons/stock_request_tier_validation/readme/CONTRIBUTORS.md
odoo/addons/stock_request_tier_validation/readme/CREDITS.md
odoo/addons/stock_request_tier_validation/readme/DESCRIPTION.md
odoo/addons/stock_request_tier_validation/readme/INSTALL.md
odoo/addons/stock_request_tier_validation/readme/USAGE.md
odoo/addons/stock_request_tier_validation/static/description/icon.png
odoo/addons/stock_request_tier_validation/static/description/index.html
odoo/addons/stock_request_tier_validation/tests/__init__.py
odoo/addons/stock_request_tier_validation/tests/test_stock_request_tier_validation.py
odoo/addons/stock_request_tier_validation/views/stock_request_order_view.xml
odoo/addons/stock_request_tier_validation/views/stock_request_view.xml
odoo_addon_stock_request_tier_validation-18.0.1.0.0.2.dist-info/METADATA
odoo_addon_stock_request_tier_validation-18.0.1.0.0.2.dist-info/WHEEL
odoo_addon_stock_request_tier_validation-18.0.1.0.0.2.dist-info/top_level.txt
odoo_addon_stock_request_tier_validation-18.0.1.0.0.2.dist-info/RECORD
